websockify_LibvirtDomain/__init__.py
websockify_LibvirtDomain-1.0.dist-info/METADATA
websockify_LibvirtDomain-1.0.dist-info/WHEEL
websockify_LibvirtDomain-1.0.dist-info/top_level.txt
websockify_LibvirtDomain-1.0.dist-info/RECORD
