Metadata-Version: 2.1
Name: websockify_LibvirtDomain
Version: 1.0
Summary: Websockify token plugin for Libvirt domains
Author-email: Stijn Rombouts <stijnrombouts@outlook.com>
Project-URL: Homepage, https://github.com/macOS-KVM/websockify-LibvirtDomain
Project-URL: Bug Tracker, https://github.com/macOS-KVM/websockify-LibvirtDomain/issues
Requires-Python: >=3.7
